traffic_light_fsm.v
module traffic_light_fsm #(
    parameter GREEN_TIME  = 5,
    parameter YELLOW_TIME = 2
)(
    input  wire clk,
    input  wire reset,
    input  wire one_sec_tick,

    output reg road_a_red,
    output reg road_a_yellow,
    output reg road_a_green,

    output reg road_b_red,
    output reg road_b_yellow,
    output reg road_b_green
);

    localparam S0 = 2'b00;   // A GREEN,  B RED
    localparam S1 = 2'b01;   // A YELLOW, B RED
    localparam S2 = 2'b10;   // A RED,    B GREEN
    localparam S3 = 2'b11;   // A RED,    B YELLOW

    reg [1:0] state;
    reg [1:0] next_state;

    // Counts seconds spent in current state
    reg [3:0] timer;

    // State and timer register
    always @(posedge clk or posedge reset) begin
        if (reset) begin
            state <= S0;
            timer <= 0;
        end
        else if (one_sec_tick) begin

            if ((state == S0 || state == S2) &&
                timer == GREEN_TIME - 1) begin

                state <= next_state;
                timer <= 0;
            end

            else if ((state == S1 || state == S3) &&
                     timer == YELLOW_TIME - 1) begin

                state <= next_state;
                timer <= 0;
            end

            else begin
                timer <= timer + 1;
            end
        end
    end

    // Next-state logic
    always @(*) begin
        case (state)
            S0: next_state = S1;
            S1: next_state = S2;
            S2: next_state = S3;
            S3: next_state = S0;
            default: next_state = S0;
        endcase
    end

    // Output logic
    always @(*) begin

        road_a_red    = 1'b0;
        road_a_yellow = 1'b0;
        road_a_green  = 1'b0;

        road_b_red    = 1'b0;
        road_b_yellow = 1'b0;
        road_b_green  = 1'b0;

        case (state)

            S0: begin
                road_a_green = 1'b1;
                road_b_red   = 1'b1;
            end

            S1: begin
                road_a_yellow = 1'b1;
                road_b_red    = 1'b1;
            end

            S2: begin
                road_a_red   = 1'b1;
                road_b_green = 1'b1;
            end

            S3: begin
                road_a_red    = 1'b1;
                road_b_yellow = 1'b1;
            end

            default: begin
                road_a_red = 1'b0;
                road_b_red = 1'b0;
            end

        endcase
    end

endmodule

traffic_light_timer.v
module traffic_light_timer #(
    parameter CLK_FREQ = 50_000_000
)(
    input  wire clk,
    input  wire reset,
    output reg  one_sec_tick
);

    reg [25:0] counter;

    always @(posedge clk or posedge reset) begin
        if (reset) begin
            counter     <= 0;
            one_sec_tick <= 0;
        end
        else begin
            if (counter == CLK_FREQ - 1) begin
                counter      <= 0;
                one_sec_tick <= 1'b1;
            end
            else begin
                counter      <= counter + 1'b1;
                one_sec_tick <= 1'b0;
            end
        end
    end

endmodule

traffic_light_fsm_tb.v
`timescale 1ns/1ps

module traffic_light_fsm_tb;

    reg clk;
    reg reset;

    wire one_sec_tick;

    wire road_a_red;
    wire road_a_yellow;
    wire road_a_green;

    wire road_b_red;
    wire road_b_yellow;
    wire road_b_green;

    integer errors;
    integer tick_count;

    traffic_light_timer #(
        .CLK_FREQ(10)
    ) timer_inst (
        .clk(clk),
        .reset(reset),
        .one_sec_tick(one_sec_tick)
    );

    traffic_light_fsm #(
        .GREEN_TIME(5),
        .YELLOW_TIME(2)
    ) dut (
        .clk(clk),
        .reset(reset),
        .one_sec_tick(one_sec_tick),
        .road_a_red(road_a_red),
        .road_a_yellow(road_a_yellow),
        .road_a_green(road_a_green),
        .road_b_red(road_b_red),
        .road_b_yellow(road_b_yellow),
        .road_b_green(road_b_green)
    );

    initial begin
        clk = 1'b0;
        forever #5 clk = ~clk;
    end

    initial begin
        reset = 1'b1;
        errors = 0;
        tick_count = 0;

        #20;
        reset = 1'b0;

        #1500;

        if (errors == 0) begin
            $display("========================================");
            $display("ALL SEQUENCE CHECKS PASSED");
            $display("========================================");
        end
        else begin
            $display("========================================");
            $display("TEST FAILED: %0d errors", errors);
            $display("========================================");
        end

        $finish;
    end

    always @(posedge clk) begin
        if (!reset && one_sec_tick) begin

            tick_count = tick_count + 1;

            $display("TICK=%0d | A_R=%b A_Y=%b A_G=%b | B_R=%b B_Y=%b B_G=%b",
                     tick_count,
                     road_a_red,
                     road_a_yellow,
                     road_a_green,
                     road_b_red,
                     road_b_yellow,
                     road_b_green);

            if (tick_count >= 1 && tick_count <= 5) begin
                if (!(road_a_green && road_b_red)) begin
                    $display("ERROR: Expected S0 at tick %0d", tick_count);
                    errors = errors + 1;
                end
            end

            if (tick_count >= 6 && tick_count <= 7) begin
                if (!(road_a_yellow && road_b_red)) begin
                    $display("ERROR: Expected S1 at tick %0d", tick_count);
                    errors = errors + 1;
                end
            end

            if (tick_count >= 8 && tick_count <= 12) begin
                if (!(road_a_red && road_b_green)) begin
                    $display("ERROR: Expected S2 at tick %0d", tick_count);
                    errors = errors + 1;
                end
            end

            if (tick_count >= 13 && tick_count <= 14) begin
                if (!(road_a_red && road_b_yellow)) begin
                    $display("ERROR: Expected S3 at tick %0d", tick_count);
                    errors = errors + 1;
                end
            end

            if (tick_count == 15) begin
                if (!(road_a_green && road_b_red)) begin
                    $display("ERROR: Expected S0 restart at tick 14");
                    errors = errors + 1;
                end
            end

        end
    end

    always @(posedge clk) begin
        if (!reset) begin

            if ((road_a_red + road_a_yellow + road_a_green) > 1) begin
                $display("ERROR: Multiple Road A lights ON at %0t", $time);
                errors = errors + 1;
            end

            if ((road_b_red + road_b_yellow + road_b_green) > 1) begin
                $display("ERROR: Multiple Road B lights ON at %0t", $time);
                errors = errors + 1;
            end

            if (road_a_green && road_b_green) begin
                $display("ERROR: BOTH ROADS GREEN at %0t", $time);
                errors = errors + 1;
            end

            if ((road_a_red + road_a_yellow + road_a_green) == 0) begin
                $display("ERROR: No Road A light active at %0t", $time);
                errors = errors + 1;
            end

            if ((road_b_red + road_b_yellow + road_b_green) == 0) begin
                $display("ERROR: No Road B light active at %0t", $time);
                errors = errors + 1;
            end

        end
    end

    initial begin
        $dumpfile("traffic_light.vcd");
        $dumpvars(0, traffic_light_fsm_tb);
    end

endmodule

traffic_light.vcd
$date
	Fri Oct  2 15:01:26 2026
$end
$version
	Icarus Verilog
$end
$timescale
	1ps
$end
$scope module traffic_light_fsm_tb $end
$var wire 1 ! road_b_yellow $end
$var wire 1 " road_b_red $end
$var wire 1 # road_b_green $end
$var wire 1 $ road_a_yellow $end
$var wire 1 % road_a_red $end
$var wire 1 & road_a_green $end
$var wire 1 ' one_sec_tick $end
$var reg 1 ( clk $end
$var reg 1 ) reset $end
$var integer 32 * errors [31:0] $end
$var integer 32 + tick_count [31:0] $end
$scope module dut $end
$var wire 1 ( clk $end
$var wire 1 ) reset $end
$var wire 1 ' one_sec_tick $end
$var parameter 32 , GREEN_TIME $end
$var parameter 2 - S0 $end
$var parameter 2 . S1 $end
$var parameter 2 / S2 $end
$var parameter 2 0 S3 $end
$var parameter 32 1 YELLOW_TIME $end
$var reg 2 2 next_state [1:0] $end
$var reg 1 & road_a_green $end
$var reg 1 % road_a_red $end
$var reg 1 $ road_a_yellow $end
$var reg 1 # road_b_green $end
$var reg 1 " road_b_red $end
$var reg 1 ! road_b_yellow $end
$var reg 2 3 state [1:0] $end
$var reg 4 4 timer [3:0] $end
$upscope $end
$scope module timer_inst $end
$var wire 1 ( clk $end
$var wire 1 ) reset $end
$var parameter 32 5 CLK_FREQ $end
$var reg 26 6 counter [25:0] $end
$var reg 1 ' one_sec_tick $end
$upscope $end
$upscope $end
$enddefinitions $end
$comment Show the parameter values. $end
$dumpall
b1010 5
b10 1
b11 0
b10 /
b1 .
b0 -
b101 ,
$end
#0
$dumpvars
b0 6
b0 4
b0 3
b1 2
b0 +
b0 *
1)
0(
0'
1&
0%
0$
0#
1"
0!
$end
#5000
1(
#10000
0(
#15000
1(
#20000
0(
0)
#25000
b1 6
1(
#30000
0(
#35000
b10 6
1(
#40000
0(
#45000
b11 6
1(
#50000
0(
#55000
b100 6
1(
#60000
0(
#65000
b101 6
1(
#70000
0(
#75000
b110 6
1(
#80000
0(
#85000
b111 6
1(
#90000
0(
#95000
b1000 6
1(
#100000
0(
#105000
b1001 6
1(
#110000
0(
#115000
1'
b0 6
1(
#120000
0(
#125000
b1 4
0'
b1 6
b1 +
1(
#130000
0(
#135000
b10 6
1(
#140000
0(
#145000
b11 6
1(
#150000
0(
#155000
b100 6
1(
#160000
0(
#165000
b101 6
1(
#170000
0(
#175000
b110 6
1(
#180000
0(
#185000
b111 6
1(
#190000
0(
#195000
b1000 6
1(
#200000
0(
#205000
b1001 6
1(
#210000
0(
#215000
1'
b0 6
1(
#220000
0(
#225000
b10 4
0'
b1 6
b10 +
1(
#230000
0(
#235000
b10 6
1(
#240000
0(
#245000
b11 6
1(
#250000
0(
#255000
b100 6
1(
#260000
0(
#265000
b101 6
1(
#270000
0(
#275000
b110 6
1(
#280000
0(
#285000
b111 6
1(
#290000
0(
#295000
b1000 6
1(
#300000
0(
#305000
b1001 6
1(
#310000
0(
#315000
1'
b0 6
1(
#320000
0(
#325000
b11 4
0'
b1 6
b11 +
1(
#330000
0(
#335000
b10 6
1(
#340000
0(
#345000
b11 6
1(
#350000
0(
#355000
b100 6
1(
#360000
0(
#365000
b101 6
1(
#370000
0(
#375000
b110 6
1(
#380000
0(
#385000
b111 6
1(
#390000
0(
#395000
b1000 6
1(
#400000
0(
#405000
b1001 6
1(
#410000
0(
#415000
1'
b0 6
1(
#420000
0(
#425000
b100 4
0'
b1 6
b100 +
1(
#430000
0(
#435000
b10 6
1(
#440000
0(
#445000
b11 6
1(
#450000
0(
#455000
b100 6
1(
#460000
0(
#465000
b101 6
1(
#470000
0(
#475000
b110 6
1(
#480000
0(
#485000
b111 6
1(
#490000
0(
#495000
b1000 6
1(
#500000
0(
#505000
b1001 6
1(
#510000
0(
#515000
1'
b0 6
1(
#520000
0(
#525000
b10 2
1$
1"
0&
b0 4
b1 3
0'
b1 6
b101 +
1(
#530000
0(
#535000
b10 6
1(
#540000
0(
#545000
b11 6
1(
#550000
0(
#555000
b100 6
1(
#560000
0(
#565000
b101 6
1(
#570000
0(
#575000
b110 6
1(
#580000
0(
#585000
b111 6
1(
#590000
0(
#595000
b1000 6
1(
#600000
0(
#605000
b1001 6
1(
#610000
0(
#615000
1'
b0 6
1(
#620000
0(
#625000
b1 4
0'
b1 6
b110 +
1(
#630000
0(
#635000
b10 6
1(
#640000
0(
#645000
b11 6
1(
#650000
0(
#655000
b100 6
1(
#660000
0(
#665000
b101 6
1(
#670000
0(
#675000
b110 6
1(
#680000
0(
#685000
b111 6
1(
#690000
0(
#695000
b1000 6
1(
#700000
0(
#705000
b1001 6
1(
#710000
0(
#715000
1'
b0 6
1(
#720000
0(
#725000
1#
1%
0"
0$
b11 2
b0 4
b10 3
0'
b1 6
b111 +
1(
#730000
0(
#735000
b10 6
1(
#740000
0(
#745000
b11 6
1(
#750000
0(
#755000
b100 6
1(
#760000
0(
#765000
b101 6
1(
#770000
0(
#775000
b110 6
1(
#780000
0(
#785000
b111 6
1(
#790000
0(
#795000
b1000 6
1(
#800000
0(
#805000
b1001 6
1(
#810000
0(
#815000
1'
b0 6
1(
#820000
0(
#825000
b1 4
0'
b1 6
b1000 +
1(
#830000
0(
#835000
b10 6
1(
#840000
0(
#845000
b11 6
1(
#850000
0(
#855000
b100 6
1(
#860000
0(
#865000
b101 6
1(
#870000
0(
#875000
b110 6
1(
#880000
0(
#885000
b111 6
1(
#890000
0(
#895000
b1000 6
1(
#900000
0(
#905000
b1001 6
1(
#910000
0(
#915000
1'
b0 6
1(
#920000
0(
#925000
b10 4
0'
b1 6
b1001 +
1(
#930000
0(
#935000
b10 6
1(
#940000
0(
#945000
b11 6
1(
#950000
0(
#955000
b100 6
1(
#960000
0(
#965000
b101 6
1(
#970000
0(
#975000
b110 6
1(
#980000
0(
#985000
b111 6
1(
#990000
0(
#995000
b1000 6
1(
#1000000
0(
#1005000
b1001 6
1(
#1010000
0(
#1015000
1'
b0 6
1(
#1020000
0(
#1025000
b11 4
0'
b1 6
b1010 +
1(
#1030000
0(
#1035000
b10 6
1(
#1040000
0(
#1045000
b11 6
1(
#1050000
0(
#1055000
b100 6
1(
#1060000
0(
#1065000
b101 6
1(
#1070000
0(
#1075000
b110 6
1(
#1080000
0(
#1085000
b111 6
1(
#1090000
0(
#1095000
b1000 6
1(
#1100000
0(
#1105000
b1001 6
1(
#1110000
0(
#1115000
1'
b0 6
1(
#1120000
0(
#1125000
b100 4
0'
b1 6
b1011 +
1(
#1130000
0(
#1135000
b10 6
1(
#1140000
0(
#1145000
b11 6
1(
#1150000
0(
#1155000
b100 6
1(
#1160000
0(
#1165000
b101 6
1(
#1170000
0(
#1175000
b110 6
1(
#1180000
0(
#1185000
b111 6
1(
#1190000
0(
#1195000
b1000 6
1(
#1200000
0(
#1205000
b1001 6
1(
#1210000
0(
#1215000
1'
b0 6
1(
#1220000
0(
#1225000
b0 2
1!
0#
1%
b0 4
b11 3
0'
b1 6
b1100 +
1(
#1230000
0(
#1235000
b10 6
1(
#1240000
0(
#1245000
b11 6
1(
#1250000
0(
#1255000
b100 6
1(
#1260000
0(
#1265000
b101 6
1(
#1270000
0(
#1275000
b110 6
1(
#1280000
0(
#1285000
b111 6
1(
#1290000
0(
#1295000
b1000 6
1(
#1300000
0(
#1305000
b1001 6
1(
#1310000
0(
#1315000
1'
b0 6
1(
#1320000
0(
#1325000
b1 4
0'
b1 6
b1101 +
1(
#1330000
0(
#1335000
b10 6
1(
#1340000
0(
#1345000
b11 6
1(
#1350000
0(
#1355000
b100 6
1(
#1360000
0(
#1365000
b101 6
1(
#1370000
0(
#1375000
b110 6
1(
#1380000
0(
#1385000
b111 6
1(
#1390000
0(
#1395000
b1000 6
1(
#1400000
0(
#1405000
b1001 6
1(
#1410000
0(
#1415000
1'
b0 6
1(
#1420000
0(
#1425000
1"
1&
0!
0%
b1 2
b0 4
b0 3
0'
b1 6
b1110 +
1(
#1430000
0(
#1435000
b10 6
1(
#1440000
0(
#1445000
b11 6
1(
#1450000
0(
#1455000
b100 6
1(
#1460000
0(
#1465000
b101 6
1(
#1470000
0(
#1475000
b110 6
1(
#1480000
0(
#1485000
b111 6
1(
#1490000
0(
#1495000
b1000 6
1(
#1500000
0(
#1505000
b1001 6
1(
#1510000
0(
#1515000
1'
b0 6
1(
